nbcheck.py
nbcheck-0.0.2.dist-info/METADATA
nbcheck-0.0.2.dist-info/WHEEL
nbcheck-0.0.2.dist-info/entry_points.txt
nbcheck-0.0.2.dist-info/licenses/LICENSE.txt
nbcheck-0.0.2.dist-info/RECORD
