Metadata-Version: 2.1
Name: nbcheck
Version: 0.0.2
Summary: Utility to check the validity of jupyter notebook files
Project-URL: homepage, https://github.com/furechan/nbcheck
Author-email: furechan <furechan@xsmail.com>
License: MIT License
License-File: LICENSE.txt
Keywords: jupyter,nbformat,notebook,utility,validation
Classifier: Operating System :: OS Independent
Classifier: Programming Language :: Python :: 3
Requires-Python: >=3.8
Requires-Dist: click
Requires-Dist: nbformat
Provides-Extra: dev
Requires-Dist: ipykernel; extra == 'dev'
